pyscitt/__init__.py
pyscitt/client.py
pyscitt/crypto.py
pyscitt/governance.py
pyscitt/local_key_sign_client.py
pyscitt/py.typed
pyscitt/receipt.py
pyscitt/verify.py
pyscitt/cli/__init__.py
pyscitt/cli/client_arguments.py
pyscitt/cli/embed_receipt_in_cose.py
pyscitt/cli/governance.py
pyscitt/cli/main.py
pyscitt/cli/pretty_receipt.py
pyscitt/cli/register.py
pyscitt/cli/retrieve_signed_claims.py
pyscitt/cli/sign.py
pyscitt/cli/split_payload.py
pyscitt/cli/validate.py
pyscitt-0.12.0.dist-info/METADATA
pyscitt-0.12.0.dist-info/WHEEL
pyscitt-0.12.0.dist-info/entry_points.txt
pyscitt-0.12.0.dist-info/top_level.txt
pyscitt-0.12.0.dist-info/RECORD
