Metadata-Version: 2.4
Name: pyscitt
Version: 0.12.0
Summary: Tools to sign claims and interact with a SCITT CCF Ledger
Home-page: https://github.com/microsoft/scitt-ccf-ledger/tree/main/pyscitt
Author: SCITT CCF Team
License: Apache License 2.0
Classifier: Development Status :: 4 - Beta
Classifier: Intended Audience :: Developers
Classifier: Intended Audience :: System Administrators
Classifier: Intended Audience :: Science/Research
Classifier: Programming Language :: Python :: 3
Classifier: License :: OSI Approved :: MIT License
Requires-Python: >=3.12
Requires-Dist: ccf==6.*
Requires-Dist: cryptography==44.*
Requires-Dist: httpx
Requires-Dist: cbor2==5.4.*
Requires-Dist: pycose==1.1.0
Requires-Dist: pyjwt
Requires-Dist: jwcrypto==1.5.*
Requires-Dist: types-jwcrypto
Requires-Dist: azure-identity
Requires-Dist: azure-confidentialledger==1.*
Dynamic: author
Dynamic: classifier
Dynamic: description
Dynamic: description-content-type
Dynamic: home-page
Dynamic: license
Dynamic: requires-dist
Dynamic: requires-python
Dynamic: summary
